trigger_dataset/__init__.py
trigger_dataset/core.py
trigger_loader/__init__.py
trigger_loader/cluster_manager.py
trigger_loader/loader.py
trigger_loader/processor.py
triggerflow/__init__.py
triggerflow/cli.py
triggerflow/core.py
triggerflow/mlflow_wrapper.py
triggerflow/interfaces/__init__.py
triggerflow/interfaces/uGT.py
triggerflow/starter/.gitignore
triggerflow/starter/README.md
triggerflow/starter/cookiecutter.json
triggerflow/starter/prompts.yml
triggerflow/starter/{{ cookiecutter.repo_name }}/.dvcignore
triggerflow/starter/{{ cookiecutter.repo_name }}/.gitignore
triggerflow/starter/{{ cookiecutter.repo_name }}/.gitlab-ci.yml
triggerflow/starter/{{ cookiecutter.repo_name }}/README.md
triggerflow/starter/{{ cookiecutter.repo_name }}/dvc.yaml
triggerflow/starter/{{ cookiecutter.repo_name }}/environment.yml
triggerflow/starter/{{ cookiecutter.repo_name }}/pyproject.toml
triggerflow/starter/{{ cookiecutter.repo_name }}/conf/README.md
triggerflow/starter/{{ cookiecutter.repo_name }}/conf/logging.yml
triggerflow/starter/{{ cookiecutter.repo_name }}/conf/base/catalog.yml
triggerflow/starter/{{ cookiecutter.repo_name }}/conf/base/parameters.yml
triggerflow/starter/{{ cookiecutter.repo_name }}/conf/base/parameters_compile.yml
triggerflow/starter/{{ cookiecutter.repo_name }}/conf/base/parameters_data_processing.yml
triggerflow/starter/{{ cookiecutter.repo_name }}/conf/base/parameters_load_data.yml
triggerflow/starter/{{ cookiecutter.repo_name }}/conf/base/parameters_model_training.yml
triggerflow/starter/{{ cookiecutter.repo_name }}/conf/base/parameters_model_validation.yml
triggerflow/starter/{{ cookiecutter.repo_name }}/conf/local/catalog.yml
triggerflow/starter/{{ cookiecutter.repo_name }}/conf/local/parameters.yml
triggerflow/starter/{{ cookiecutter.repo_name }}/conf/local/parameters_compile.yml
triggerflow/starter/{{ cookiecutter.repo_name }}/conf/local/parameters_data_processing.yml
triggerflow-0.3.3.dist-info/METADATA
triggerflow-0.3.3.dist-info/WHEEL
triggerflow-0.3.3.dist-info/entry_points.txt
triggerflow-0.3.3.dist-info/top_level.txt
triggerflow-0.3.3.dist-info/RECORD
