Metadata-Version: 2.4
Name: triggerflow
Version: 0.3.3
Summary: Utilities for ML models targeting hardware triggers
Classifier: Programming Language :: Python :: 3
Classifier: License :: OSI Approved :: MIT License
Classifier: Operating System :: OS Independent
Requires-Python: >=3.11
Requires-Dist: cookiecutter>=2.3
Requires-Dist: PyYAML>=6
Requires-Dist: Jinja2>=3
Requires-Dist: mlflow==2.21.0
Requires-Dist: kedro==1.0.0
Provides-Extra: dev
Requires-Dist: pytest-cov~=3.0; extra == "dev"
Requires-Dist: pytest-mock<2.0,>=1.7.1; extra == "dev"
Requires-Dist: pytest~=7.2; extra == "dev"
Requires-Dist: ruff~=0.1.8; extra == "dev"
Provides-Extra: extended
Requires-Dist: coffea; extra == "extended"
Requires-Dist: dask; extra == "extended"
Requires-Dist: pyarrow; extra == "extended"
Requires-Dist: pandas==2.0.3; extra == "extended"
Requires-Dist: uproot4==4.0.0; extra == "extended"
Requires-Dist: pyarrow==17.0.0; extra == "extended"
Requires-Dist: hist==2.7.3; extra == "extended"
Requires-Dist: mlflow==2.21.0; extra == "extended"
Requires-Dist: tensorflow==2.13.0; extra == "extended"
Requires-Dist: QKeras==0.9.0; extra == "extended"
Requires-Dist: keras==2.13.1; extra == "extended"
Requires-Dist: numpy; extra == "extended"
Requires-Dist: pyparsing; extra == "extended"
Requires-Dist: PyYAML; extra == "extended"
Requires-Dist: matplotlib; extra == "extended"
Requires-Dist: mplhep; extra == "extended"
Requires-Dist: h5py; extra == "extended"
Requires-Dist: xxhash; extra == "extended"
Requires-Dist: shap; extra == "extended"
Requires-Dist: awkward-pandas; extra == "extended"
Requires-Dist: qonnx==0.4.0; extra == "extended"
Requires-Dist: tf_keras; extra == "extended"
Requires-Dist: tf2onnx; extra == "extended"
Requires-Dist: hls4ml; extra == "extended"
Requires-Dist: conifer; extra == "extended"
